nsescraper/__init__.py
nsescraper/nifty_indices.pickle
nsescraper/nsescraper.py
nsescraper/nsescraper.svg
nsescraper/option_indices.pickle
nsescraper/test_nsescraper.py
nsescraper-0.0.8.data/data/nsescraper/nifty_indices.pickle
nsescraper-0.0.8.data/data/nsescraper/nsescraper.svg
nsescraper-0.0.8.data/data/nsescraper/option_indices.pickle
nsescraper-0.0.8.dist-info/LICENSE
nsescraper-0.0.8.dist-info/METADATA
nsescraper-0.0.8.dist-info/WHEEL
nsescraper-0.0.8.dist-info/top_level.txt
nsescraper-0.0.8.dist-info/RECORD
