Metadata-Version: 2.1
Name: nsescraper
Version: 0.0.8
Summary: A scraper for https://www.nseindia.com
Home-page: https://github.com/U77w41/
Author: Ujjwal Chowdhury
Author-email: <u77w41@gmail.com>
License: MIT
Keywords: python,NSE,NIFTY,scraping
Classifier: Programming Language :: Python :: 3
Classifier: License :: OSI Approved :: MIT License
Classifier: Operating System :: OS Independent
Requires-Python: >=3.8
License-File: LICENSE
Requires-Dist: pandas
Requires-Dist: pytz
Requires-Dist: urllib3
Requires-Dist: python-dateutil
